[
    {
        "name": "張自強",
        "phone": "0952-077-223"
    },
    {
        "name": "林俊育",
        "phone": "0977-001-438"
    },
    {
        "name": "簡中信",
        "phone": "0938-776-528"
    },
    {
        "name": "王以誠",
        "phone": "0905-283-066"
    },
    {
        "name": "蕭立安",
        "phone": "0978-073-363"
    },
    {
        "name": "王子倫",
        "phone": "0932-197-039"
    },
    {
        "name": "俞翰蒼",
        "phone": "0972-061-551"
    },
    {
        "name": "賴冠宇",
        "phone": "0919-809-856"
    },
    {
        "name": "蔡欣展",
        "phone": ""
    },
    {
        "name": "鄭子煜",
        "phone": "0916-737-807"
    },
    {
        "name": "駱奕辰",
        "phone": "0903-505-365"
    },
    {
        "name": "林柏霖",
        "phone": "0958-520-080"
    },
    {
        "name": "王凱賢",
        "phone": "0986-167-167"
    },
    {
        "name": "彭學裕",
        "phone": "0975-271-170"
    },
    {
        "name": "楊立豪",
        "phone": "0900-632-931"
    },
    {
        "name": "王俊凱",
        "phone": "0978-520-770"
    },
    {
        "name": "張明智",
        "phone": "0917-992-406"
    },
    {
        "name": "黃文林",
        "phone": "0983-883-745"
    },
    {
        "name": "翁灝文",
        "phone": "0956-911-810"
    },
    {
        "name": "丁晉丞",
        "phone": ""
    },
    {
        "name": "陳柏宇",
        "phone": "0918-293-308"
    },
    {
        "name": "劉芝穎",
        "phone": "0986-899-556"
    },
    {
        "name": "林達強",
        "phone": ""
    },
    {
        "name": "馮祥誠",
        "phone": "0970-806-852"
    },
    {
        "name": "陳勇霖",
        "phone": "0976-945-419"
    },
    {
        "name": "詹淳景",
        "phone": "0931-313-239"
    },
    {
        "name": "廖偉強",
        "phone": "0958-051-488"
    },
    {
        "name": "吳浩唯",
        "phone": "0975-689-516"
    },
    {
        "name": "何晏",
        "phone": "0912-900-098"
    },
    {
        "name": "葉兆倫",
        "phone": "0953-868-897"
    },
    {
        "name": "王群丞",
        "phone": "0966-183-515"
    },
    {
        "name": "鐘佑翰",
        "phone": "0987-094-222"
    },
    {
        "name": "陳墩翰",
        "phone": "0919-687-497"
    },
    {
        "name": "王威程",
        "phone": "0919-419-423"
    },
    {
        "name": "陳為廷",
        "phone": "0909-479-236"
    },
    {
        "name": "劉經甫",
        "phone": "0928-021-286"
    },
    {
        "name": "賈永佳",
        "phone": "0939-550-892"
    },
    {
        "name": "施佑霖",
        "phone": "0989-172-490"
    },
    {
        "name": "陳尚謙",
        "phone": "0919-336-789"
    },
    {
        "name": "張展碩",
        "phone": "0986-751-817"
    },
    {
        "name": "李勇廷",
        "phone": "0932-022-713"
    },
    {
        "name": "余玳麒",
        "phone": "0931-083-142"
    },
    {
        "name": "黃柏智",
        "phone": "0925-836-752"
    },
    {
        "name": "楊凱鈞",
        "phone": "0975-061-488"
    },
    {
        "name": "朱洪睦",
        "phone": "0932-644-186"
    },
    {
        "name": "劉鎮瑋",
        "phone": "0975-289-066"
    },
    {
        "name": "張屹",
        "phone": "0970-828-505"
    },
    {
        "name": "張家誠",
        "phone": "0921-037-657"
    },
    {
        "name": "王子豪",
        "phone": "0925-012-322"
    },
    {
        "name": "陳志成",
        "phone": "0980-513-161"
    },
    {
        "name": "施季甫",
        "phone": "0935-220-204"
    },
    {
        "name": "郭兆揚",
        "phone": "0978-723-908"
    },
    {
        "name": "何孟勳",
        "phone": "0970-628-266"
    },
    {
        "name": "蔡政軒",
        "phone": "0222-705-288"
    },
    {
        "name": "呂其宥",
        "phone": "0973-880-383"
    },
    {
        "name": "蔡政洋",
        "phone": "0988-778-638"
    },
    {
        "name": "葉宛宜",
        "phone": "0989-580-125"
    },
    {
        "name": "吳忠益",
        "phone": "0988-896-110"
    },
    {
        "name": "謝昇紘",
        "phone": "0920-963-767"
    },
    {
        "name": "張育弘",
        "phone": "0982-484-800"
    },
    {
        "name": "鄭浩仙",
        "phone": "0909-035-578"
    },
    {
        "name": "？泰瑋",
        "phone": "0952-333-732"
    },
    {
        "name": "廖信翔",
        "phone": "09xx-xxx-xxx"
    },
    {
        "name": "X宥逸",
        "phone": ""
    },
    {
        "name": "孫浩桓",
        "phone": ""
    },
    {
        "name": "鄭仲淳",
        "phone": "0989511595"
    },
    {
        "name": "賴家世",
        "phone": "0917-619-937"
    }
]